sharkradar/__init__.py
sharkradar/Config/Config.py
sharkradar/Config/__init__.py
sharkradar/Controller/Controller.py
sharkradar/Controller/__init__.py
sharkradar/Main/Main.py
sharkradar/Main/__init__.py
sharkradar/NonPy_UI_Build/build/asset-manifest.json
sharkradar/NonPy_UI_Build/build/favicon.ico
sharkradar/NonPy_UI_Build/build/index.html
sharkradar/NonPy_UI_Build/build/logo192.png
sharkradar/NonPy_UI_Build/build/logo512.png
sharkradar/NonPy_UI_Build/build/manifest.json
sharkradar/NonPy_UI_Build/build/precache-manifest.495c379238612a82c5b15c8ab6dc77f3.js
sharkradar/NonPy_UI_Build/build/robots.txt
sharkradar/NonPy_UI_Build/build/service-worker.js
sharkradar/NonPy_UI_Build/build/static/css/2.6ca2aa04.chunk.css
sharkradar/NonPy_UI_Build/build/static/css/2.6ca2aa04.chunk.css.map
sharkradar/NonPy_UI_Build/build/static/js/2.2b475963.chunk.js
sharkradar/NonPy_UI_Build/build/static/js/2.2b475963.chunk.js.map
sharkradar/NonPy_UI_Build/build/static/js/main.6b516733.chunk.js
sharkradar/NonPy_UI_Build/build/static/js/main.6b516733.chunk.js.map
sharkradar/NonPy_UI_Build/build/static/js/runtime~main.8159d949.js
sharkradar/NonPy_UI_Build/build/static/js/runtime~main.8159d949.js.map
sharkradar/NonPy_UI_Build/build/static/media/brand-icons.13db00b7.eot
sharkradar/NonPy_UI_Build/build/static/media/brand-icons.a046592b.woff
sharkradar/NonPy_UI_Build/build/static/media/brand-icons.a1a749e8.svg
sharkradar/NonPy_UI_Build/build/static/media/brand-icons.c5ebe0b3.ttf
sharkradar/NonPy_UI_Build/build/static/media/brand-icons.e8c322de.woff2
sharkradar/NonPy_UI_Build/build/static/media/flags.9c74e172.png
sharkradar/NonPy_UI_Build/build/static/media/icons.0ab54153.woff2
sharkradar/NonPy_UI_Build/build/static/media/icons.8e3c7f55.eot
sharkradar/NonPy_UI_Build/build/static/media/icons.962a1bf3.svg
sharkradar/NonPy_UI_Build/build/static/media/icons.b87b9ba5.ttf
sharkradar/NonPy_UI_Build/build/static/media/icons.faff9214.woff
sharkradar/NonPy_UI_Build/build/static/media/outline-icons.701ae6ab.eot
sharkradar-1.2.0.dist-info/LICENSE.rst
sharkradar-1.2.0.dist-info/METADATA
sharkradar-1.2.0.dist-info/WHEEL
sharkradar-1.2.0.dist-info/entry_points.txt
sharkradar-1.2.0.dist-info/top_level.txt
sharkradar-1.2.0.dist-info/RECORD
