Metadata-Version: 2.1
Name: sharkradar
Version: 1.2.0
Summary: Lightweight micro service registry and discovery tool, compatible with any HTTP based microservice
Home-page: https://bmonikraj.github.io/sharkradar
Author: Monik Raj Behera
Author-email: bmonikraj@gmail.com
Maintainer: Preetam Keshari Nahak
Maintainer-email: preetamnahak@gmail.com
License: BSD-3-Clause
Project-URL: Documentation, https://github.com/bmonikraj/sharkradar/wiki
Project-URL: Code, https://github.com/bmonikraj/sharkradar
Project-URL: Issue tracker, https://github.com/bmonikraj/sharkradar/issues
Platform: UNKNOWN
Classifier: Development Status :: 4 - Beta
Classifier: Environment :: Other Environment
Classifier: Environment :: Console
Classifier: Intended Audience :: Developers
Classifier: License :: OSI Approved :: BSD License
Classifier: Operating System :: MacOS :: MacOS X
Classifier: Operating System :: POSIX
Classifier: Operating System :: Microsoft :: Windows
Classifier: Programming Language :: Python
Classifier: Programming Language :: Python :: 3
Classifier: Programming Language :: Python :: 3.7
Classifier: Programming Language :: Python :: 3 :: Only
Classifier: Topic :: Internet
Classifier: Topic :: Utilities
Classifier: Topic :: Software Development
Classifier: Topic :: Adaptive Technologies
Classifier: Topic :: System :: Distributed Computing
Classifier: Topic :: Internet :: WWW/HTTP
Classifier: Topic :: Internet :: WWW/HTTP :: WSGI
Classifier: Topic :: Internet :: WWW/HTTP :: WSGI :: Server
Classifier: Topic :: Internet :: WWW/HTTP :: Dynamic Content
Requires-Python: >=2.7, >=3
Requires-Dist: flask (>=1.0.1)
Requires-Dist: pysqlite3 (>=0.2.0)
Requires-Dist: waitress (>=1.2.0)
Requires-Dist: click (>=7.0)
Requires-Dist: pyfiglet (>=0.8.0)
Requires-Dist: termcolor (>=1.1.0)
Requires-Dist: colorama (>=0.4.1)
